furu/__init__.py
furu/adapters/__init__.py
furu/adapters/submitit.py
furu/config.py
furu/core/__init__.py
furu/core/furu.py
furu/core/list.py
furu/dashboard/__init__.py
furu/dashboard/__main__.py
furu/dashboard/api/__init__.py
furu/dashboard/api/models.py
furu/dashboard/api/routes.py
furu/dashboard/frontend/dist/assets/index-BXAIKNNr.css
furu/dashboard/frontend/dist/assets/index-BjyrY-Zz.js
furu/dashboard/frontend/dist/favicon.svg
furu/dashboard/frontend/dist/index.html
furu/dashboard/main.py
furu/dashboard/scanner.py
furu/errors.py
furu/execution/__init__.py
furu/execution/context.py
furu/execution/local.py
furu/execution/paths.py
furu/execution/plan.py
furu/execution/plan_utils.py
furu/execution/slurm_dag.py
furu/execution/slurm_pool.py
furu/execution/slurm_spec.py
furu/execution/submitit_factory.py
furu/migrate.py
furu/migration.py
furu/runtime/__init__.py
furu/runtime/env.py
furu/runtime/logging.py
furu/runtime/overrides.py
furu/runtime/tracebacks.py
furu/serialization/__init__.py
furu/serialization/migrations.py
furu/serialization/serializer.py
furu/storage/__init__.py
furu/storage/metadata.py
furu/storage/migration.py
furu/storage/state.py
furu/testing.py
furu-0.0.6.dist-info/WHEEL
furu-0.0.6.dist-info/entry_points.txt
furu-0.0.6.dist-info/METADATA
furu-0.0.6.dist-info/RECORD
