Metadata-Version: 2.3
Name: furu
Version: 0.0.6
Summary: Cacheable, nested pipelines for Python. Define computations as configs; furu handles caching, state tracking, and result reuse across runs.
Author: Herman Brunborg
Author-email: Herman Brunborg <herman@brunborg.com>
Requires-Dist: chz>=0.4.0
Requires-Dist: cloudpickle>=3.1.1
Requires-Dist: pydantic>=2.12.5
Requires-Dist: python-dotenv>=1.0.0
Requires-Dist: rich>=14.2.0
Requires-Dist: submitit>=1.5.3
Requires-Dist: fastapi>=0.109.0 ; extra == 'dashboard'
Requires-Dist: uvicorn[standard]>=0.27.0 ; extra == 'dashboard'
Requires-Dist: typer>=0.9.0 ; extra == 'dashboard'
Requires-Python: >=3.12
Provides-Extra: dashboard
